labtest/__init__.py
labtest/cli.py
labtest/config.py
labtest/configobj.py
labtest/filesystem.py
labtest/instance.py
labtest/secrets.py
labtest/services.py
labtest/provider/__init__.py
labtest/provider/base_secret.py
labtest/provider/base_service.py
labtest/provider/base_state.py
labtest/provider/aws/__init__.py
labtest/provider/aws/rds.py
labtest/provider/aws/repository.py
labtest/provider/aws/secrets.py
labtest/provider/aws/state.py
labtest/provider/docker/__init__.py
labtest/provider/docker/mysql.py
labtest/provider/docker/templates/systemd-backing.conf.template
labtest/provider/local/__init__.py
labtest/provider/local/state.py
labtest/templates/docker-build
labtest/templates/systemd-test.conf.template
labtest-0.4.8.dist-info/METADATA
labtest-0.4.8.dist-info/RECORD
labtest-0.4.8.dist-info/WHEEL
labtest-0.4.8.dist-info/entry_points.txt
labtest-0.4.8.dist-info/top_level.txt
