Metadata-Version: 2.1
Name: labtest
Version: 0.4.8
Summary: Build an isolated test lab for running software in containers.
Home-page: https://github.com/CityOfBoston/labtest
Author: Corey Oordt
Author-email: coreyoordt@gmail.com
License: BSD license
Keywords: labtest
Platform: UNKNOWN
Classifier: Development Status :: 3 - Alpha
Classifier: Intended Audience :: Developers
Classifier: License :: OSI Approved :: BSD License
Classifier: Natural Language :: English
Classifier: Environment :: Console
Classifier: Topic :: Software Development :: Testing
Classifier: Topic :: Utilities
Classifier: Programming Language :: Python :: 2
Classifier: Programming Language :: Python :: 2.7
Requires-Python: ==2.7.*
Requires-Dist: fabric (<2.0)
Requires-Dist: click
Requires-Dist: python-dotenv
Requires-Dist: oyaml
Requires-Dist: future
